{
  "info": {
    "name": "Kingdom Foods - Bulk Upload",
    "description": "Bulk upload dishes to database and Cloudinary",
    "schema": "https://schema.getpostman.com/json/collection/v2.1.0/collection.json"
  },
  "item": [
    {
      "name": "1. Admin Login",
      "request": {
        "method": "POST",
        "header": [
          {
            "key": "Content-Type",
            "value": "application/json"
          }
        ],
        "body": {
          "mode": "raw",
          "raw": "{\n  \"email\": \"admin@example.com\",\n  \"password\": \"your-password\"\n}"
        },
        "url": {
          "raw": "http://localhost:5000/api/auth/login",
          "protocol": "http",
          "host": ["localhost"],
          "port": "5000",
          "path": ["api", "auth", "login"]
        }
      }
    },
    {
      "name": "2. Bulk Upload Dishes",
      "request": {
        "method": "POST",
        "header": [
          {
            "key": "Content-Type",
            "value": "application/json"
          },
          {
            "key": "Authorization",
            "value": "Bearer {{jwt_token}}"
          }
        ],
        "body": {
          "mode": "raw",
          "raw": "{\n  \"dishes\": [\n    {\n      \"name\": \"Mango Juice\",\n      \"price\": 100,\n      \"category\": \"Fresh Juices\",\n      \"description\": \"Freshly squeezed mango juice rich in vitamins.\",\n      \"imagePath\": \"C:\\\\Users\\\\Mohan\\\\Downloads\\\\kajuanjeer.jpg\"\n    },\n    {\n      \"name\": \"Apple Juice\",\n      \"price\": 70,\n      \"category\": \"Fresh Juices\",\n      \"description\": \"Refreshing and healthy fresh apple juice.\",\n      \"imagePath\": \"C:\\\\Users\\\\Mohan\\\\Downloads\\\\kajuanjeer.jpg\"\n    },\n    {\n      \"name\": \"Orange Juice\",\n      \"price\": 70,\n      \"category\": \"Fresh Juices\",\n      \"description\": \"Citrusy and revitalizing fresh orange juice.\",\n      \"imagePath\": \"C:\\\\Users\\\\Mohan\\\\Downloads\\\\kajuanjeer.jpg\"\n    }\n  ]\n}"
        },
        "url": {
          "raw": "http://localhost:5000/menu/bulk/upload",
          "protocol": "http",
          "host": ["localhost"],
          "port": "5000",
          "path": ["menu", "bulk", "upload"]
        }
      }
    },
    {
      "name": "3. Get All Dishes (Verify Upload)",
      "request": {
        "method": "GET",
        "header": [],
        "url": {
          "raw": "http://localhost:5000/menu",
          "protocol": "http",
          "host": ["localhost"],
          "port": "5000",
          "path": ["menu"]
        }
      }
    }
  ],
  "variable": [
    {
      "key": "jwt_token",
      "value": "your-jwt-token-here",
      "type": "string"
    }
  ]
}
